simple_text2sql-1.0.3.dist-info/licenses/LICENSE
text2sql/__init__.py
text2sql/database.py
text2sql/text2sql.py
text2sql/resources/prompts/text2sql/optimizesql.md
text2sql/resources/prompts/text2sql/references.md
text2sql/resources/prompts/text2sql/text2sql.md
text2sql/resources/sqls/ddl_mysql.sql
text2sql/resources/sqls/ddl_postgres.sql
text2sql/utils/__init__.py
text2sql/utils/ai.py
text2sql/utils/path.py
text2sql/utils/strings.py
simple_text2sql-1.0.3.dist-info/METADATA
simple_text2sql-1.0.3.dist-info/WHEEL
simple_text2sql-1.0.3.dist-info/top_level.txt
simple_text2sql-1.0.3.dist-info/RECORD
