Metadata-Version: 2.4
Name: simple-text2sql
Version: 1.0.3
Summary: A simple implementation of Text2SQL.
Project-URL: Homepage, https://github.com/secretpot/text2sql
Project-URL: Repository, https://github.com/secretpot/text2sql
Requires-Python: >=3.12.3
License-File: LICENSE
Requires-Dist: langchain-ollama>=0.3.3
Requires-Dist: langchain-openai>=0.3.19
Requires-Dist: psycopg2-binary>=2.9.10
Requires-Dist: pydantic>=2.11.5
Requires-Dist: pymilvus>=2.5.10
Requires-Dist: pymysql>=1.1.1
Requires-Dist: sqlalchemy>=2.0.41
Dynamic: license-file
